<?xml version="1.0" ?>
<system id="730dff4a-bc63-11e6-b892-c8e0eb171521" xmlns="http://www.plejd.com/schema/System" xmlns:xsi="http://www.w3.org/2001/XMLSchema-instance" xsi:schemaLocation="http://www.plejd.com/schema/System ../../../idoru-xmlschema/System.xsd">
  <label value="Sasha"/>
  <locations>
    <level id="lowerdeck">
      <areas>
        <area id="crew_mess">
          <zones>
            <zone id="main">
              <devices>
                <device value="lighting.keypad_76_1_crew_mess"/>
                <device value="lighting76_1-crew_mess"/>
              </devices>
            </zone>
          </zones>
        </area>
        <area id="main_beach_club">
          <zones>
            <zone id="main">
              <devices>
                <device value="lighting.keypad_92_1_main_beach_club"/>
                <device value="lighting92_1-main_beach_club"/>
              </devices>
            </zone>
          </zones>
        </area>
        <area id="guest_suite">
          <zones>
            <zone id="main">
              <devices>
                <device value="lighting.keypad_83_1_guest_suite"/>
                <device value="lighting83_1-guest_suite"/>
              </devices>
            </zone>
          </zones>
        </area>
      </areas>
    </level>
    <level id="maindeck">
      <areas>
        <area id="galley">
          <zones>
            <zone id="main">
              <devices>
                <device value="lighting.keypad_94_1_galley"/>
                <device value="lighting94_1-galley"/>
              </devices>
            </zone>
          </zones>
        </area>
        <area id="bar">
          <zones>
            <zone id="main">
              <devices>
                <device value="lighting.keypad_56_1_bar"/>
                <device value="lighting56_1-bar"/>
              </devices>
            </zone>
          </zones>
        </area>
        <area id="owner_stateroom">
          <zones>
            <zone id="main">
              <devices>
                <device value="lighting.keypad_73_1_owner_stateroom"/>
                <device value="lighting73_1-owner_stateroom"/>
              </devices>
            </zone>
          </zones>
        </area>
      </areas>
    </level>
  </locations>
  <devices>
    <device id="lighting">
      <prototype value="vbh:13698:lighting"/>
      <interface id="main">
        <channel id="network">
          <provider value="network"/>
          <address value="10.10.134.30"/>
          <autoconnect value="true"/>
        </channel>
      </interface>
      <connections>
        <connection port="keypad_76_1_crew_mess.out" targetdevice="lighting76_1-crew_mess" targetport="in"/>
        <connection port="keypad_92_1_main_beach_club.out" targetdevice="lighting92_1-main_beach_club" targetport="in"/>
        <connection port="keypad_83_1_guest_suite.out" targetdevice="lighting83_1-guest_suite" targetport="in"/>
        <connection port="keypad_94_1_galley.out" targetdevice="lighting94_1-galley" targetport="in"/>
        <connection port="keypad_56_1_bar.out" targetdevice="lighting56_1-bar" targetport="in"/>
        <connection port="keypad_73_1_owner_stateroom.out" targetdevice="lighting73_1-owner_stateroom" targetport="in"/>
      </connections>
    </device>
    <device id="lighting76_1-crew_mess">
      <prototype value="generic:light:1"/>
      <label value="Lighting"/>
    </device>
    <device id="lighting92_1-main_beach_club">
      <prototype value="generic:light:1"/>
      <label value="Lighting"/>
    </device>
    <device id="lighting83_1-guest_suite">
      <prototype value="generic:light:1"/>
      <label value="Lighting"/>
    </device>
    <device id="lighting94_1-galley">
      <prototype value="generic:light:1"/>
      <label value="Lighting"/>
    </device>
    <device id="lighting56_1-bar">
      <prototype value="generic:light:1"/>
      <label value="Lighting"/>
    </device>
    <device id="lighting73_1-owner_stateroom">
      <prototype value="generic:light:1"/>
      <label value="Lighting"/>
    </device>
  </devices>
</system>